omniwatermask/__init__.py
omniwatermask/__version__.py
omniwatermask/download_models.py
omniwatermask/model_download_links.csv
omniwatermask/raster_helpers.py
omniwatermask/target_builders.py
omniwatermask/vector_cache.py
omniwatermask/water_inf_helpers.py
omniwatermask/water_inf_pipeline.py
omniwatermask-0.4.0.dist-info/licenses/LICENSE
omniwatermask-0.4.0.dist-info/METADATA
omniwatermask-0.4.0.dist-info/WHEEL
omniwatermask-0.4.0.dist-info/top_level.txt
omniwatermask-0.4.0.dist-info/RECORD
