Metadata-Version: 2.4
Name: omniwatermask
Version: 0.4.0
Summary: Python library for water segmentation in high to moderate resolution remotely sensed imagery
Author-email: Nick Wright <nicholas.wright@dpird.wa.gov.au>
License-Expression: MIT
Project-URL: Homepage, https://github.com/DPIRD-DMA/OmniWaterMask
Keywords: sentinel-2,landsat,maxar,planetscope,satellite,water,remote-sensing,mask
Requires-Python: >=3.9
License-File: LICENSE
Requires-Dist: omnicloudmask>=1.0.7
Requires-Dist: opencv-python>=4.9.0.80
Requires-Dist: geopandas>=1.0
Requires-Dist: osmnx>=2.0.0
Requires-Dist: scipy>=1.10.0
Requires-Dist: pyarrow>=10.0.0
Requires-Dist: huggingface_hub>=0.28.1
Requires-Dist: safetensors>=0.3.0
Requires-Dist: gdown>=5.1.0
Requires-Dist: rasterio>=1.3
Requires-Dist: timm>=0.9
Requires-Dist: torch>=2.3.0
Requires-Dist: tqdm>=4.0
Requires-Dist: platformdirs>=4.0.0
Dynamic: license-file
